datacataloglib/__init__.py
datacataloglib/data_catalog_interfaces.py
datacataloglib/request_helper.py
datacataloglib/utils.py
datacataloglib-0.0.33.dist-info/METADATA
datacataloglib-0.0.33.dist-info/WHEEL
datacataloglib-0.0.33.dist-info/top_level.txt
datacataloglib-0.0.33.dist-info/RECORD
