Metadata-Version: 2.1
Name: datacataloglib
Version: 0.0.33
Summary: data catalog service library
Home-page: UNKNOWN
Author: Data Engineering team
Author-email: support@aisingapore.org
License: UNKNOWN
Keywords: python,data engineering data catalog service library
Platform: UNKNOWN
Classifier: Programming Language :: Python :: 3
